papertools/Cfg.py
papertools/Console.py
papertools/Dir.py
papertools/Encasings.py
papertools/File.py
papertools/Groq.py
papertools/Misc.py
papertools/Ollama.py
papertools/Timer.py
papertools/WebServify.py
papertools/Webhook.py
papertools/__init__.py
papertools-1.17.dist-info/METADATA
papertools-1.17.dist-info/WHEEL
papertools-1.17.dist-info/top_level.txt
papertools-1.17.dist-info/RECORD
