Metadata-Version: 2.4
Name: papertools
Version: 1.17
Home-page: https://www.github.com/PaperTarsier692/papertools
Author: PaperTarsier692
Requires-Dist: requests
Dynamic: author
Dynamic: description
Dynamic: description-content-type
Dynamic: home-page
Dynamic: requires-dist
